{
  "source_file": "kim-20250930.htm",
  "form_type": "10-Q",
  "item1_clean": null,
  "item7_clean": null,
  "item2_clean": "The increase in Revenues from rental properties, net of $85.3 million for the nine months ended September 30, 2025, as compared to the corresponding period in 2024, is primarily from (i) a net increase in revenues from tenants of $46.3 million, primarily due to an increase in leasing activity and net growth in the current portfolio, (ii) an increase in revenues of $33.3 million due to properties acquired during 2025 and 2024, (iii) an increase in lease termination fee income of $6.4 million and (iv) an increase in net straight-line rental income of $0.7 million, primarily due to changes in reserves, partially offset by (v) a decrease in revenues of $1.4 million due to dispositions during 2025 and 2024.\nThe increase in Real estate taxes of $9.3 million for the nine months ended September 30, 2025, as compared to the corresponding period in 2024, is primarily due to (i) an increase of $2.7 million due to properties acquired during 2025 and 2024, (ii) an overall increase in assessed values in the current portfolio and (iii) timing of real estate tax refunds.\nOperating and maintenance –\nThe increase in Operating and maintenance expense of $3.7 million for the three months ended September 30, 2025, as compared to the corresponding period in 2024, is primarily due to (i) an increase in repairs and maintenance expense of $2.9 million and (ii) an increase of $1.7 million resulting from properties acquired during 2025 and 2024, partially offset by (iii) a decrease in insurance expense of $0.8 million.\nThe increase in Operating and maintenance expense of $10.8 million for the nine months ended September 30, 2025, as compared to the corresponding period in 2024, is primarily due to (i) an increase in repairs and maintenance expense of $6.3 million, (ii) an increase of $4.4 million resulting from properties acquired during 2025 and 2024, (iii) an increase of $1.3 million in snow removal costs and (iv) an overall increase in operating costs of $1.2 million, partially offset by (v) a decrease in insurance expense of $2.4 million.\nGeneral and administrative –\nThe decrease in General and administrative expense of $4.2 million for the three months ended September 30, 2025, as compared to the corresponding period in 2024, is primarily due to (i) a decrease in employee-related benefit expenses of $3.2 million and (ii) a decrease in professional fees and corporate expenses of $0.9 million.\nThe decrease in General and administrative expense of $6.8 million for the nine months ended September 30, 2025, as compared to the corresponding period in 2024, is primarily due to (i) a decrease in employee-related benefit expenses of $5.5 million and (ii) a decrease in professional fees and corporate expenses of $1.1 million.\nImpairment charges –\n\nThe increase in Depreciation and amortization of $13.6 million for the three months ended September 30, 2025, as compared to the corresponding period in 2024, is primarily due to (i) an increase of $7.9 million due to depreciation commencing on certain redevelopment projects and tenant improvement projects that were placed into service during 2025 and 2024 and (ii) an increase of $6.5 million resulting from properties acquired during 2025 and 2024, partially offset by (iii) a net decrease of $0.8 million due to fully depreciated assets and write-offs, primarily from demolition, vacated tenants and dispositions during 2025 and 2024.\nThe increase in Depreciation and amortization of $25.5 million for the nine months ended September 30, 2025, as compared to the corresponding period in 2024, is primarily due to (i) an increase of $24.2 million due to depreciation commencing on certain redevelopment projects and tenant improvement projects that were placed into service during 2025 and 2024 and (ii) an increase of $19.9 million resulting from properties acquired during 2025 and 2024, partially offset by (iii) a net decrease of $18.6 million due to fully depreciated assets and write-offs, primarily from demolition, vacated tenants and dispositions during 2025 and 2024.\n\nGain on sale of properties –\nDuring the nine months ended September 30, 2025, the Company disposed of two operating properties and three land parcels, in separate transactions, for an aggregate sales price of $71.6 million, which resulted in aggregate gains of $43.5 million. During the nine months ended September 30, 2024, the Company disposed of 11 operating properties and seven land parcels, in separate transactions, for an aggregate sales price of $254.1 million, which resulted in aggregate gains of $0.9 million.\nOther (expense)/income, net –\nThe change in Other (expense)/income, net of $12.6 million for the three months ended September 30, 2025, as compared to the corresponding period in 2024, is primarily due to (i) a decrease of $5.5 million due to mark-to-market fluctuations of an embedded derivative liability, (ii) $3.1 million in higher costs associated with potential transactions for which the Company is no longer pursuing, (iii) a decrease in interest income of $1.9 million resulting from lower cash balances during 2025 as compared to 2024 and (iv) an increase in environmental remediation costs of $1.1 million.\nThe change in Other (expense)/income, net of $20.0 million for the nine months ended September 30, 2025, as compared to the corresponding period in 2024, is primarily due to (i) a decrease in interest income of $8.6 million resulting from lower cash balances during 2025 as compared to 2024, (ii) $4.1 million in higher costs associated with potential transactions for which the Company is no longer pursuing, (iii) a decrease of $1.6 million from insurance proceeds received during 2025 as compared to 2024, (iv) an increase in environmental remediation costs of $1.5 million, (v) a decrease in dividend income of $1.4 million, primarily due to the sale of the remaining shares of ACI common stock held by the Company during 2024, and (vi) a decrease of $1.2 million from settlement proceeds of a contract during 2024.\nMortgage and other financing income, net –\n\nThe Parent Company guarantees the unsecured debt instruments of Kimco OP, including the Credit Facility. These guarantees by the Parent Company are full, irrevocable, unconditional and absolute joint and several guarantees to the holders of each series of such unsecured debt instruments.\nIn connection with the construction of its development/redevelopment projects and related infrastructure, certain public agencies require posting of performance and surety bonds to guarantee that the Company’s obligations are satisfied. These bonds expire upon the completion of the improvements and infrastructure. As of September 30, 2025, the Company had $18.1 million in performance and surety bonds outstanding.\nIn connection with its intention to continue to qualify as a REIT for U.S. federal income tax purposes, the Company expects to continue paying regular dividends to its stockholders. These dividends will be paid from operating cash flows. The Company’s Board of Directors will continue to evaluate the Company’s dividend policy on a quarterly basis as it monitors sources of capital and evaluates the impact of the economy and capital markets availability on operating fundamentals. Since cash used to pay dividends reduces amounts available for capital investment, the Company generally intends to maintain a dividend payout ratio which reserves such amounts as it considers necessary for the expansion and renovation of shopping centers in its portfolio, debt reduction, the acquisition of interests in new properties and other investments as suitable opportunities arise and such other factors as the Board of Directors considers appropriate. Cash dividends paid for common and preferred stock for the nine months ended September 30, 2025 and 2024 were $531.1 million and $507.8 million, respectively.\nAlthough the Company receives substantially all of its rental payments on a monthly basis, it generally intends to continue paying dividends quarterly. Amounts accumulated in advance of each quarterly distribution will be invested by the Company in short-term money market or other suitable instruments. The Company’s objective is to establish a dividend level that maintains compliance with the Company’s REIT taxable income distribution requirements. On July 29, 2025, the Company’s Board of Directors declared a quarterly dividend with respect to the Company’s classes of cumulative redeemable preferred shares (Classes L, M and N), which were paid on October 15, 2025, to shareholders of record on October 1, 2025. In addition, the Company’s Board of Directors declared a quarterly cash dividend of $0.25 per common share, which was paid on September 19, 2025 to shareholders of record on September 5, 2025.\n\nRelated to gains, impairments, depreciation on properties and gains/(losses) on sales of marketable securities and derivatives, where applicable.\nReflects the potential impact of convertible preferred shares and certain units if converted to common stock at the beginning of the period. FFO available to the Company’s common shareholders would be increased by $2,186 and $2,464 for the three months ended September 30, 2025 and 2024, respectively. FFO available to the Company’s common shareholders would be increased by $6,233 and $7,370 for the nine months ended September 30, 2025 and 2024, respectively. The effect of other certain convertible units would have an anti-dilutive effect upon the calculation of FFO available to the Company’s common shareholders per share. Accordingly, the impact of such conversion has not been included in the determination of diluted FFO per share calculations.\nIncludes merger-related charges of $25.2 million for the nine months ended September 30, 2024.\nSame Property Net Operating Income (“Same property NOI”)\nSame property NOI is a supplemental non-GAAP financial measure of real estate companies’ operating performance and should not be considered an alternative to net income in "
}